{
  "project_info": {
    "project_number": "1032397750938",
    "firebase_url": "https://my-app-12524-default-rtdb.asia-southeast1.firebasedatabase.app",
    "project_id": "my-app-12524",
    "storage_bucket": "my-app-12524.appspot.com"
  },
  "client": [
    {
      "client_info": {
        "mobilesdk_app_id": "1:1032397750938:android:191804315822d01e9c9523",
        "android_client_info": {
          "package_name": "com.mygolfapp"
        }
      },
      "oauth_client": [
        {
          "client_id": "1032397750938-1avgkkruq6es0s1jajjabbigfegg50ln.apps.googleusercontent.com",
          "client_type": 3
        }
      ],
      "api_key": [
        {
          "current_key": "AIzaSyBBQQ5mFVyP2jbih1b5xDzdSSqHaUitysI"
        }
      ],
      "services": {
        "appinvite_service": {
          "other_platform_oauth_client": [
            {
              "client_id": "1032397750938-1avgkkruq6es0s1jajjabbigfegg50ln.apps.googleusercontent.com",
              "client_type": 3
            },
            {
              "client_id": "1032397750938-50m563g9icdhfaktm0k2tosiqbgmofma.apps.googleusercontent.com",
              "client_type": 2,
              "ios_info": {
                "bundle_id": "com.salutjuillet.myfirebaseApp"
              }
            }
          ]
        }
      }
    },
    {
      "client_info": {
        "mobilesdk_app_id": "1:1032397750938:android:ac5bee1484a0a3d99c9523",
        "android_client_info": {
          "package_name": "com.salutjuillet.myfirebaseApp"
        }
      },
      "oauth_client": [
        {
          "client_id": "1032397750938-1avgkkruq6es0s1jajjabbigfegg50ln.apps.googleusercontent.com",
          "client_type": 3
        }
      ],
      "api_key": [
        {
          "current_key": "AIzaSyBBQQ5mFVyP2jbih1b5xDzdSSqHaUitysI"
        }
      ],
      "services": {
        "appinvite_service": {
          "other_platform_oauth_client": [
            {
              "client_id": "1032397750938-1avgkkruq6es0s1jajjabbigfegg50ln.apps.googleusercontent.com",
              "client_type": 3
            },
            {
              "client_id": "1032397750938-50m563g9icdhfaktm0k2tosiqbgmofma.apps.googleusercontent.com",
              "client_type": 2,
              "ios_info": {
                "bundle_id": "com.salutjuillet.myfirebaseApp"
              }
            }
          ]
        }
      }
    }
  ],
  "configuration_version": "1"
}